{
    "$schema": "http://schema.management.azure.com/schemas/2015-01-01/deploymentParameters.json#",
    "contentVersion": "1.0.0.0",
    "parameters": {
        "uniqueDnsName": {
            "value": "apptmdns"
        },
        "primaryResourceGroup": {
            "value": "app-1-rg"
        },
        "primaryPublicIpName": {
            "value": "v1-gwy-ip"
        },
        "secondaryResourceGroup": {
            "value": "app-2-rg"
        },
        "secondaryPublicIpName": {
            "value": "v2-gwy-ip"
        },
        "primaryLocation": {
            "value": "West US"
        },
        "secondaryLocation": {
            "value": "East US"
        },
        "trafficManagerProfileName": {
            "value": "app-dev-tm"
        },
        "monitorPath": {
            "value": "/"
        }
    }
}
